.DS_Store
tmart/.DS_Store
tmart/Aerosol.py
tmart/Atmosphere.py
tmart/Surface.py
tmart/__init__.py
tmart/tm_OT.py
tmart/tm_calcref.py
tmart/tm_geometry.py
tmart/tm_intersect.py
tmart/tm_move.py
tmart/tm_sampling.py
tmart/tm_water.py
tmart/tmart.py
tmart/tmart2.py
tmart/AEC/AEC.py
tmart/AEC/__init__.py
tmart/AEC/anci_download.py
tmart/AEC/anci_get_AER.py
tmart/AEC/anci_get_OWV.py
tmart/AEC/anci_list_files.py
tmart/AEC/compute_gas_transmittance.py
tmart/AEC/compute_masks.py
tmart/AEC/fillnan.py
tmart/AEC/get_AOT.py
tmart/AEC/get_ancillary.py
tmart/AEC/get_parameters.py
tmart/AEC/identify_input.py
tmart/AEC/identify_sensor.py
tmart/AEC/irradiance_correction.py
tmart/AEC/plot_water_extent.py
tmart/AEC/read_PRISMA_north.py
tmart/AEC/read_PRISMA_vaa.py
tmart/AEC/read_atm_info.py
tmart/AEC/read_config.py
tmart/AEC/read_metadata_L8.py
tmart/AEC/read_metadata_Landsat.py
tmart/AEC/read_metadata_S2.py
tmart/AEC/read_xml_S2.py
tmart/AEC/read_xml_S2_scene.py
tmart/AEC/reflectance_correction.py
tmart/AEC/run.py
tmart/AEC/run_acoliteL1R.py
tmart/AEC/run_regular.py
tmart/AEC/unzip.py
tmart/AEC/write_atm_info.py
tmart/ancillary/conifer_forest.csv
tmart/ancillary/dry_beach_sand.csv
tmart/ancillary/lawn_grass.csv
tmart/ancillary/soil.csv
tmart/ancillary/vegetation.csv
tmart/ancillary/water.csv
tmart/ancillary/water_chl1.csv
tmart/ancillary/wet_beach_sand.csv
tmart/ancillary/whitecap_factor.csv
tmart/ancillary/aerosolSPF/BiomassBurning.csv
tmart/ancillary/aerosolSPF/Continental.csv
tmart/ancillary/aerosolSPF/Desert.csv
tmart/ancillary/aerosolSPF/Maritime.csv
tmart/ancillary/aerosolSPF/Stratospheric.csv
tmart/ancillary/aerosolSPF/Urban.csv
tmart/config/config.txt
tmart/surface_rho/__init__.py
tmart/surface_rho/calculate.py
tmart-2.6.1.dist-info/METADATA
tmart-2.6.1.dist-info/WHEEL
tmart-2.6.1.dist-info/top_level.txt
tmart-2.6.1.dist-info/RECORD
