Metadata-Version: 2.4
Name: tmart
Version: 2.6.1
Summary: Modelling and correcting for the adjacency effect in aquatic remote sensing
Author: Yulun Wu
Classifier: Intended Audience :: Science/Research
Classifier: Topic :: Scientific/Engineering :: Atmospheric Science
Classifier: Topic :: Scientific/Engineering :: Physics
Classifier: Topic :: Software Development :: Libraries :: Python Modules
Classifier: Programming Language :: Python :: 3
Classifier: License :: OSI Approved :: GNU General Public License v3 or later (GPLv3+)
Classifier: Operating System :: OS Independent
Requires-Python: >=3.8
Requires-Dist: scipy
Requires-Dist: pathos
Requires-Dist: matplotlib
Requires-Dist: netCDF4
Requires-Dist: mgrs
Requires-Dist: geopandas
Requires-Dist: requests
Requires-Dist: pandas
Dynamic: author
Dynamic: classifier
Dynamic: description
Dynamic: description-content-type
Dynamic: requires-dist
Dynamic: requires-python
Dynamic: summary
